{
    "name": "pixelart",
    "creator": "schraf",
    "created_at": "December 17, 2020",
    "size": "1.4 KB",
    "image": "data/schraf/pixelart/schraf_pixelart.png",
    "tags": [],
    "description": "<p><a href=\"https://youtu.be/3v0x1DSNLe0\" rel=\"nofollow\">Explications en vid\u00e9o ici</a></p> <p>Dans la vid\u00e9o j\u2019utilise <code>monotonic</code> pour temporiser le jeu, dans la version ci-dessous j\u2019ai simplifi\u00e9 en ne mettant que <code>sleep</code>.</p> <h2>Pixel Art</h2> <ul> <li>Restez appuy\u00e9 sur une des touches 7, 8 ou 9 en vous d\u00e9pla\u00e7ant pour obtenir une frise color\u00e9e</li> <li>Appuyez sur 2 fl\u00e8ches de direction pour vous d\u00e9placer en diagonal</li> <li>Changez la valeur de <b>d = 8</b> par une autre valeur pour obtenir un quadrillage plus gros ou plus petit. Essayez par exemple avec d = 2 !</li> <li>N\u2019oubliez pas de prendre en photo vos oeuvres avant de sortir du programme ;-)</li> </ul> <p></p>"
}